ocr_gather-0.1.0.dist-info/METADATA
ocr_gather-0.1.0.dist-info/WHEEL
ocr_gather/__init__.py
ocr_gather-0.1.0.dist-info/RECORD
