Metadata-Version: 2.1
Name: ocr-gather
Version: 0.1.0
Summary: Some third-party ocr api wrapper
Author-Email: centyuan <centyuan@outlook.com>
License: MIT
Requires-Python: >=3.8
